clean_transaction/__init__.py
clean_transaction-0.0.0.dist-info/LICENSE
clean_transaction-0.0.0.dist-info/METADATA
clean_transaction-0.0.0.dist-info/WHEEL
clean_transaction-0.0.0.dist-info/top_level.txt
clean_transaction-0.0.0.dist-info/RECORD
