Metadata-Version: 2.1
Name: clean-transaction
Version: 0.0.0
Summary: WIP
Home-page: https://github.com/internetimagery/clean-transaction
Author: Jason Dixon
Author-email: jason.dixon.email@gmail.com
License: UNKNOWN
Platform: UNKNOWN
